{
  "date": "20260221",
  "count": 20,
  "articles": [
    {
      "title": "Re: [閒聊] CPI不到1",
      "date": "2/16",
      "url": "https://www.ptt.cc/bbs/home-sale/M.1771215301.A.B47.html"
    },
    {
      "title": "Re: [新聞] 獨/房市降溫衝擊?高雄工程行遭控「積百",
      "date": "2/08",
      "url": "https://www.ptt.cc/bbs/home-sale/M.1770542861.A.E10.html"
    },
    {
      "title": "[閒聊] 川普:%$(*&*%*& (某些人不愛聽的話)",
      "date": "1/30",
      "url": "https://www.ptt.cc/bbs/home-sale/M.1769732143.A.CB4.html"
    },
    {
      "title": "Re: [閒聊] 原來還有免息，無限期開槓這招",
      "date": "1/27",
      "url": "https://www.ptt.cc/bbs/home-sale/M.1769527597.A.A17.html"
    },
    {
      "title": "Re: [閒聊] 沒人發現採光越來越不重要了嗎？",
      "date": "1/25",
      "url": "https://www.ptt.cc/bbs/home-sale/M.1769332920.A.FAD.html"
    },
    {
      "title": "Re: [新聞] 新青安斷頭潮只是夢一場？他揭銀行審核真",
      "date": "1/23",
      "url": "https://www.ptt.cc/bbs/home-sale/M.1769159040.A.D96.html"
    },
    {
      "title": "Re: [閒聊] 還是不能理解為何首爾精華區噴爆",
      "date": "1/20",
      "url": "https://www.ptt.cc/bbs/home-sale/M.1768901077.A.47B.html"
    },
    {
      "title": "Re: [閒聊] 用持有成本看型態，台灣其實是買斷型住宅",
      "date": "1/16",
      "url": "https://www.ptt.cc/bbs/home-sale/M.1768496639.A.9FD.html"
    },
    {
      "title": "Re: [新聞] 住宅法修正初審通過 鼓勵包租、社宅納入",
      "date": "1/01",
      "url": "https://www.ptt.cc/bbs/home-sale/M.1767246763.A.4F5.html"
    },
    {
      "title": "Re: [閒聊] 房產、收入與斬殺線",
      "date": "12/29",
      "url": "https://www.ptt.cc/bbs/home-sale/M.1766995080.A.6AA.html"
    },
    {
      "title": "Re: [閒聊] 少子化你應該先想想如何自救=.=",
      "date": "12/27",
      "url": "https://www.ptt.cc/bbs/home-sale/M.1766832873.A.9C6.html"
    },
    {
      "title": "Re: [請益] 美中自動駕駛廣泛營運對房價有影響嗎",
      "date": "12/27",
      "url": "https://www.ptt.cc/bbs/home-sale/M.1766803270.A.A84.html"
    },
    {
      "title": "Re: [請益] 請問現在房市到底是火熱還是急凍啊？",
      "date": "12/25",
      "url": "https://www.ptt.cc/bbs/home-sale/M.1766650620.A.E3A.html"
    },
    {
      "title": "Re: [閒聊] 高房價只會造成隨機殺人越來越多吧？",
      "date": "12/23",
      "url": "https://www.ptt.cc/bbs/home-sale/M.1766478976.A.8FE.html"
    },
    {
      "title": "Re: [閒聊] 高房價只會造成隨機殺人越來越多吧？",
      "date": "12/21",
      "url": "https://www.ptt.cc/bbs/home-sale/M.1766321581.A.0A7.html"
    },
    {
      "title": "Re: [閒聊] 隨機殺人常發生在捷運,捷運宅會跌嗎",
      "date": "12/20",
      "url": "https://www.ptt.cc/bbs/home-sale/M.1766228285.A.3CC.html"
    },
    {
      "title": "Re: [閒聊] 為什麼今天營建股還會上漲？",
      "date": "12/19",
      "url": "https://www.ptt.cc/bbs/home-sale/M.1766117935.A.EA4.html"
    },
    {
      "title": "Re: [請益]如何才能人人買得起?房市健全稅收高",
      "date": "12/16",
      "url": "https://www.ptt.cc/bbs/home-sale/M.1765864062.A.88E.html"
    },
    {
      "title": "Re: [閒聊] 餐廳的機能重要嗎",
      "date": "12/15",
      "url": "https://www.ptt.cc/bbs/home-sale/M.1765773196.A.142.html"
    },
    {
      "title": "Re: [閒聊] 俄羅斯對烏東佔領區不動產的最新法案",
      "date": "12/15",
      "url": "https://www.ptt.cc/bbs/home-sale/M.1765756501.A.367.html"
    }
  ]
}